{
  "conan": {
    "packageId": "ca6b19bf89270552244fca32806dded803132e76",
    "reference": "ogg/1.3.4@",
    "remote": "conan-center"
  },
  "library": {
    "name": "ogg",
    "reference": "ogg/1.3.4"
  },
  "packager": {
    "name": "@ffi-packager/ffi-packager",
    "url": "https://github.com/node-ffi-packager",
    "version": "2.0.0"
  },
  "platform": {
    "headerFiles": [
      {
        "name": "./include/ogg/config_types.h",
        "path": "./include/ogg/config_types.h.js"
      },
      {
        "name": "./include/ogg/ogg.h",
        "path": "./include/ogg/ogg.h.js"
      },
      {
        "name": "./include/ogg/os_types.h",
        "path": "./include/ogg/os_types.h.js"
      }
    ],
    "libraryDependencies": {},
    "libraryFiles": ["./lib/libogg.0.8.4.dylib"],
    "name": "macos-x86_64"
  }
}
